kg_core/__communication.py
kg_core/__init__.py
kg_core/kg.py
kg_core/oauth.py
kg_core/py.typed
kg_core/request.py
kg_core/response.py
kg_core/test_response.py
ebrains_kg_core-0.9.20.dist-info/LICENSE
ebrains_kg_core-0.9.20.dist-info/METADATA
ebrains_kg_core-0.9.20.dist-info/WHEEL
ebrains_kg_core-0.9.20.dist-info/top_level.txt
ebrains_kg_core-0.9.20.dist-info/RECORD
