Metadata-Version: 2.1
Name: ebrains_kg_core
Version: 0.9.20
Home-page: https://github.com/HumanBrainProject/kg-core-sdks
Author: EBRAINS
Author-email: kg@ebrains.eu
Keywords: EBRAINS,Knowledge Graph,KG
License-File: LICENSE
Requires-Dist: requests
Requires-Dist: pydantic
